<annotation>
  <filename>1SDDDDDC4_Camera2_07-19-19_15-26-090074.png</filename>
  <folder>VOC2007</folder><source><database>Unknown</database></source><size>
    <width>1920</width>
    <height>1088</height>
  </size>
  <object>
    <pose>Unspecified</pose><truncated>0</truncated><difficult>0</difficult><name>SERRANUSANNULARIS-170024201</name>
    <bndbox>
      <xmin>365</xmin>
      <ymin>945</ymin>
      <xmax>442</xmax>
      <ymax>1049</ymax>
    </bndbox>
  </object>
  <object>
    <pose>Unspecified</pose><truncated>0</truncated><difficult>0</difficult><name>HOLACANTHUSBERMUDENSIS-170290102</name>
    <bndbox>
      <xmin>1484</xmin>
      <ymin>579</ymin>
      <xmax>1635</xmax>
      <ymax>719</ymax>
    </bndbox>
  </object>
</annotation>